claude/__init__.py
claude/client.py
claude/constants.py
claude/core.py
claude/localhost.py
claude/utils.py
claude/models/__init__.py
claude/models/decorator.py
claude/models/exceptions.py
python_claude_api-0.1.0.dist-info/LICENSE
python_claude_api-0.1.0.dist-info/METADATA
python_claude_api-0.1.0.dist-info/WHEEL
python_claude_api-0.1.0.dist-info/entry_points.txt
python_claude_api-0.1.0.dist-info/top_level.txt
python_claude_api-0.1.0.dist-info/RECORD
